pypart.py
pypart-0.1.6.dist-info/LICENSE
pypart-0.1.6.dist-info/WHEEL
pypart-0.1.6.dist-info/METADATA
pypart-0.1.6.dist-info/RECORD
