Metadata-Version: 2.1
Name: pypart
Version: 0.1.6
Summary: Couples pipeline transformers with their parameters for easier reuse of transformers
License: GPL-3.0+
Author: Benjamin Murauer
Author-email: b.murauer@posteo.de
Requires-Python: >=3.6.1,<4.0.0
Classifier: License :: OSI Approved :: GNU General Public License v3 or later (GPLv3+)
Classifier: Programming Language :: Python :: 3
Classifier: Programming Language :: Python :: 3.7
Classifier: Programming Language :: Python :: 3.8
Classifier: Programming Language :: Python :: 3.9
Requires-Dist: pandas (>=1.1.0,<2.0.0)
Requires-Dist: pipelinehelper (>=0.7.8,<0.8.0)
Requires-Dist: sklearn (>=0.0,<0.1)
